{
  "relationship_id": "nsw_revenue_tax_interactions",
  "description": "Relationship mappings between NSW revenue taxes",
  "relationships": [
    {
      "primary_tax": "land_tax",
      "secondary_tax": "duties",
      "relationship_type": "complementary",
      "interaction_rules": {
        "timing": "duties_at_purchase_land_tax_annual",
        "value_impact": "no_direct_impact_separate_calculations",
        "exemption_overlap": "ppr_exemption_may_apply_to_both"
      }
    },
    {
      "primary_tax": "first_home_buyer_grant",
      "secondary_tax": "duties",
      "relationship_type": "beneficial",
      "interaction_rules": {
        "timing": "grant_available_at_purchase",
        "value_impact": "may_qualify_for_duty_exemption",
        "eligibility": "first_home_buyer_criteria_must_be_met"
      }
    }
  ]
}